vidimg_utils/__init__.py
vidimg_utils/object_detector/detection.py
vidimg_utils/object_detector/detector.py
vidimg_utils/object_detector/yolov3_detector.py
vidimg_utils/screen/utils.py
vidimg_utils/video/stream.py
vidimg_utils-0.0.2.dist-info/METADATA
vidimg_utils-0.0.2.dist-info/WHEEL
vidimg_utils-0.0.2.dist-info/licenses/LICENSE
vidimg_utils-0.0.2.dist-info/RECORD
