Metadata-Version: 2.1
Name: vidimg_utils
Version: 0.0.2
Summary: A small utils to work with video and images
Project-URL: Homepage, https://bitbucket.org/maksymfedoryshyn/video-and-imaging-tools/src/master/
Author-email: Maksym Fedoryshyn <maksym.fedoryshyn@gmail.com>
License-File: LICENSE
Classifier: License :: OSI Approved :: MIT License
Classifier: Operating System :: OS Independent
Classifier: Programming Language :: Python :: 3
Requires-Python: >=3.7
